faviconx/__init__.py
faviconx/__main__.py
faviconx-1.0.0.dist-info/LICENSE
faviconx-1.0.0.dist-info/METADATA
faviconx-1.0.0.dist-info/WHEEL
faviconx-1.0.0.dist-info/entry_points.txt
faviconx-1.0.0.dist-info/top_level.txt
faviconx-1.0.0.dist-info/RECORD
