Metadata-Version: 2.1
Name: faviconx
Version: 1.0.0
Summary: A command-line tool for generating favicons from source images
Home-page: https://github.com/rapidrabbitsoft/faviconx
Author: FaviconX Team
Author-email: contact@faviconx.dev
Keywords: favicon,icon,generator,cli,web,pwa,apple-touch-icon,android
Classifier: Development Status :: 5 - Production/Stable
Classifier: Intended Audience :: Developers
Classifier: Topic :: Multimedia :: Graphics :: Graphics Conversion
Classifier: Topic :: Software Development :: Libraries :: Python Modules
Classifier: Topic :: Internet :: WWW/HTTP :: Site Management
Classifier: License :: OSI Approved :: MIT License
Classifier: Programming Language :: Python :: 3
Classifier: Programming Language :: Python :: 3.9
Classifier: Programming Language :: Python :: 3.10
Classifier: Programming Language :: Python :: 3.11
Classifier: Programming Language :: Python :: 3.12
Classifier: Programming Language :: Python :: 3.13
Classifier: Operating System :: OS Independent
Classifier: Environment :: Console
Classifier: Topic :: Utilities
Requires-Python: >=3.9
License-File: LICENSE
Requires-Dist: Pillow>=10.0.0
Requires-Dist: click>=8.0.0
Requires-Dist: cairosvg>=2.7.0
